pypkgs_cn_mds_524/__init__.py
pypkgs_cn_mds_524/pypkgs_cn_mds_524.py
pypkgs_cn_mds_524-0.1.0.dist-info/LICENSE
pypkgs_cn_mds_524-0.1.0.dist-info/WHEEL
pypkgs_cn_mds_524-0.1.0.dist-info/METADATA
pypkgs_cn_mds_524-0.1.0.dist-info/RECORD
